ai_todo/__init__.py
ai_todo/cli/__init__.py
ai_todo/cli/config_ops.py
ai_todo/cli/main.py
ai_todo/cli/system_ops.py
ai_todo/cli/tamper_ops.py
ai_todo/cli/utility_ops.py
ai_todo/cli/commands/__init__.py
ai_todo/core/__init__.py
ai_todo/core/config.py
ai_todo/core/coordination.py
ai_todo/core/empty_trash.py
ai_todo/core/exceptions.py
ai_todo/core/file_ops.py
ai_todo/core/github_client.py
ai_todo/core/migrations.py
ai_todo/core/prune.py
ai_todo/core/task.py
ai_todo/core/updater.py
ai_todo/core/version_constraints.py
ai_todo/mcp/__init__.py
ai_todo/mcp/__main__.py
ai_todo/mcp/server.py
ai_todo/parsers/__init__.py
ai_todo/utils/__init__.py
ai_todo/utils/git.py
ai_todo/utils/logging.py
ai_todo-4.0.0b3.dist-info/licenses/LICENSE
ai_todo-4.0.0b3.dist-info/METADATA
ai_todo-4.0.0b3.dist-info/WHEEL
ai_todo-4.0.0b3.dist-info/entry_points.txt
ai_todo-4.0.0b3.dist-info/top_level.txt
ai_todo-4.0.0b3.dist-info/RECORD
