Metadata-Version: 2.4
Name: ai-todo
Version: 4.0.0b3
Summary: AI-Agent First TODO List Tracker with MCP and CLI interfaces
Author-email: Oliver Ratzesberger <fxstein@gmail.com>
License: Apache-2.0
Project-URL: Homepage, https://github.com/fxstein/ai-todo
Project-URL: Documentation, https://github.com/fxstein/ai-todo/tree/main/docs
Project-URL: Repository, https://github.com/fxstein/ai-todo.git
Project-URL: Issues, https://github.com/fxstein/ai-todo/issues
Keywords: todo,ai,mcp,cli,productivity,agent
Classifier: Development Status :: 5 - Production/Stable
Classifier: Environment :: Console
Classifier: Intended Audience :: Developers
Classifier: License :: OSI Approved :: Apache Software License
Classifier: Operating System :: OS Independent
Classifier: Programming Language :: Python :: 3
Classifier: Programming Language :: Python :: 3.10
Classifier: Programming Language :: Python :: 3.11
Classifier: Programming Language :: Python :: 3.12
Classifier: Programming Language :: Python :: 3.13
Classifier: Programming Language :: Python :: 3.14
Classifier: Topic :: Software Development :: Libraries :: Python Modules
Classifier: Topic :: Utilities
Requires-Python: >=3.10
License-File: LICENSE
Requires-Dist: mcp>=0.1.0
Requires-Dist: click>=8.1.0
Requires-Dist: pyyaml>=6.0.1
Requires-Dist: requests>=2.32.0
Requires-Dist: pygithub>=2.5.0
Requires-Dist: fastmcp<3.0.0,>=2.14.4
Provides-Extra: dev
Requires-Dist: pytest>=8.0.0; extra == "dev"
Requires-Dist: pytest-asyncio>=0.23.0; extra == "dev"
Requires-Dist: pytest-cov>=5.0.0; extra == "dev"
Requires-Dist: ruff>=0.5.0; extra == "dev"
Requires-Dist: mypy>=1.10.0; extra == "dev"
Requires-Dist: pre-commit>=3.7.0; extra == "dev"
Requires-Dist: build>=1.0.0; extra == "dev"
Requires-Dist: twine>=5.0.0; extra == "dev"
Requires-Dist: ascii-guard>=1.5.0; extra == "dev"
Requires-Dist: types-requests>=2.31.0; extra == "dev"
Requires-Dist: types-pyyaml>=6.0.12.12; extra == "dev"
Dynamic: license-file
